pysetup/__init__.py
pysetupper-0.0.1.dist-info/METADATA
pysetupper-0.0.1.dist-info/WHEEL
pysetupper-0.0.1.dist-info/top_level.txt
pysetupper-0.0.1.dist-info/RECORD
