Metadata-Version: 2.4
Name: PYSetupper
Version: 0.0.1
Summary: Ready Setupper
Requires-Dist: PyQt6
